pi4ioe5v9xxxx/__init__.py
pi4ioe5v9xxxx/pi4ioe5v9xxxx.py
pi4ioe5v9xxxx-0.0.2.dist-info/LICENSE
pi4ioe5v9xxxx-0.0.2.dist-info/METADATA
pi4ioe5v9xxxx-0.0.2.dist-info/WHEEL
pi4ioe5v9xxxx-0.0.2.dist-info/top_level.txt
pi4ioe5v9xxxx-0.0.2.dist-info/RECORD
