Metadata-Version: 2.1
Name: pi4ioe5v9xxxx
Version: 0.0.2
Summary: Driver for pi4ioe5v0xxxx I2C IO expander chips
Home-page: https://github.com/antonverburg/pi4ioe5v9xxxx
Author: Anton Verburg
Author-email: info@tec-V.nl
License: UNKNOWN
Platform: UNKNOWN
Classifier: Programming Language :: Python :: 3
Classifier: License :: OSI Approved :: GNU General Public License v3 or later (GPLv3+)
Classifier: Operating System :: OS Independent
Requires-Python: >=3.7
Requires-Dist: smbus2
